ddumpy/__init__.py
ddumpy/__main__.py
ddumpy/cli.py
ddumpy/helpers/__init__.py
ddumpy/helpers/console.py
ddumpy/helpers/docker.py
ddumpy/postgresql.py
ddumpy-0.1.1.dist-info/LICENSE.md
ddumpy-0.1.1.dist-info/METADATA
ddumpy-0.1.1.dist-info/WHEEL
ddumpy-0.1.1.dist-info/entry_points.txt
ddumpy-0.1.1.dist-info/RECORD
