Metadata-Version: 2.1
Name: ddumpy
Version: 0.1.1
Summary: CLI for easily interacting with database dumps without having a local instance running by using docker
Home-page: https://github.com/Noah-Labs-Development/dumpy
License: LICENSE.md
Author: vipierozan99
Author-email: victorpierozan@gmail.com
Requires-Python: >=3.10,<4.0
Classifier: License :: Other/Proprietary License
Classifier: Programming Language :: Python :: 3
Classifier: Programming Language :: Python :: 3.10
Classifier: Programming Language :: Python :: 3.11
Classifier: Programming Language :: Python :: 3.12
Requires-Dist: click (>=8.1.7,<9.0.0)
Requires-Dist: docker (>=6.1.3,<7.0.0)
Requires-Dist: rich (>=13.7.0,<14.0.0)
Requires-Dist: typing-extensions (>=4.8.0,<5.0.0)
Project-URL: Repository, https://github.com/Noah-Labs-Development/dumpy
